{"format":2,"version":"5.1","globals":"6f970bb3fd818c0086bb8745517713d8","files":{"todo___init___py":{"hash":"af9d0d0de0ea3b71d198bc63f1499a7d","index":{"nums":[1,0,0,0,0,0,0],"html_filename":"todo___init___py.html","relative_filename":"todo/__init__.py"}},"todo_admin_py":{"hash":"07b1d1b690b3e75f341360f23ad79dcb","index":{"nums":[1,3,0,0,0,0,0],"html_filename":"todo_admin_py.html","relative_filename":"todo/admin.py"}},"todo_apps_py":{"hash":"2cb8b88da52588c3ed30bf12e2154cc9","index":{"nums":[1,3,0,0,0,0,0],"html_filename":"todo_apps_py.html","relative_filename":"todo/apps.py"}},"todo_forms_py":{"hash":"bf9bccda37d125a96d8a6211ec92ce90","index":{"nums":[1,6,0,0,0,0,0],"html_filename":"todo_forms_py.html","relative_filename":"todo/forms.py"}},"todo_migrations_0001_initial_py":{"hash":"40565dba6eae18487ea319481443c0e7","index":{"nums":[1,6,0,0,0,0,0],"html_filename":"todo_migrations_0001_initial_py.html","relative_filename":"todo/migrations/0001_initial.py"}},"todo_migrations___init___py":{"hash":"af9d0d0de0ea3b71d198bc63f1499a7d","index":{"nums":[1,0,0,0,0,0,0],"html_filename":"todo_migrations___init___py.html","relative_filename":"todo/migrations/__init__.py"}},"todo_models_py":{"hash":"e1cb02cda0835dbf66a2a5fe8d17c397","index":{"nums":[1,6,0,0,0,0,0],"html_filename":"todo_models_py.html","relative_filename":"todo/models.py"}},"todo_tests_forms_py":{"hash":"d4f7a4b516239b3947b643ac9704fde0","index":{"nums":[1,10,0,0,0,0,0],"html_filename":"todo_tests_forms_py.html","relative_filename":"todo/tests_forms.py"}},"todo_tests_models_py":{"hash":"cc65017fe9f7cb01e8aa4b6971262478","index":{"nums":[1,17,0,0,0,0,0],"html_filename":"todo_tests_models_py.html","relative_filename":"todo/tests_models.py"}},"todo_tests_views_py":{"hash":"83b3b9d9aa2446e1bdeabbb10efb7037","index":{"nums":[1,40,0,0,0,0,0],"html_filename":"todo_tests_views_py.html","relative_filename":"todo/tests_views.py"}},"todo_views_py":{"hash":"801e4142dfd8f5fc79e2e3f7beb6a33b","index":{"nums":[1,29,0,1,0,0,0],"html_filename":"todo_views_py.html","relative_filename":"todo/views.py"}},"todo_test_app_py":{"hash":"3297e3abb58601fe2b45eaf74371776c","index":{"nums":[1,7,0,0,0,0,0],"html_filename":"todo_test_app_py.html","relative_filename":"todo/test_app.py"}}}}